langchain_google_memorystore_redis/__init__.py
langchain_google_memorystore_redis/chat_message_history.py
langchain_google_memorystore_redis/loader.py
langchain_google_memorystore_redis/py.typed
langchain_google_memorystore_redis/saver.py
langchain_google_memorystore_redis/vectorstore.py
langchain_google_memorystore_redis/version.py
langchain_google_memorystore_redis-0.3.0.dist-info/LICENSE
langchain_google_memorystore_redis-0.3.0.dist-info/METADATA
langchain_google_memorystore_redis-0.3.0.dist-info/WHEEL
langchain_google_memorystore_redis-0.3.0.dist-info/top_level.txt
langchain_google_memorystore_redis-0.3.0.dist-info/RECORD
