Metadata-Version: 2.1
Name: langchain-google-memorystore-redis
Version: 0.3.0
Summary: LangChain integrations for Google Cloud Memorystore
Author-email: Google LLC <googleapis-packages@google.com>
License: 
Project-URL: Homepage, https://github.com/googleapis/langchain-google-memorystore-redis-python
Project-URL: Repository, https://github.com/googleapis/langchain-google-memorystore-redis-python.git
Project-URL: Bug Tracker, https://github.com/googleapis/langchain-google-memorystore-redis-python/issues
Project-URL: Changelog, https://github.com/googleapis/langchain-google-memorystore-redis-python/blob/main/CHANGELOG.md
Classifier: Intended Audience :: Developers
Classifier: License :: OSI Approved :: Apache Software License
Classifier: Programming Language :: Python
Classifier: Programming Language :: Python :: 3
Classifier: Programming Language :: Python :: 3.8
Classifier: Programming Language :: Python :: 3.9
Classifier: Programming Language :: Python :: 3.10
Classifier: Programming Language :: Python :: 3.11
Classifier: Programming Language :: Python :: 3.12
Requires-Python: >=3.8
License-File: LICENSE
Requires-Dist: langchain-core <1.0.0,>=0.1.1
Requires-Dist: langchain-community <1.0.0,>=0.0.18
Requires-Dist: redis <6.0.0,>=5.0.0
Requires-Dist: numpy <2.0.0,>=1.24.4
Provides-Extra: test
Requires-Dist: black[jupyter] ==24.8.0 ; extra == 'test'
Requires-Dist: isort ==5.13.2 ; extra == 'test'
Requires-Dist: mypy ==1.11.1 ; extra == 'test'
Requires-Dist: pytest-asyncio ==0.23.8 ; extra == 'test'
Requires-Dist: pytest ==8.3.2 ; extra == 'test'
Requires-Dist: pytest-cov ==5.0.0 ; extra == 'test'
